sgep/__init__.py
sgep-0.0.2.dist-info/METADATA
sgep-0.0.2.dist-info/WHEEL
sgep-0.0.2.dist-info/licenses/LICENSE
sgep-0.0.2.dist-info/RECORD
