Metadata-Version: 2.1
Name: sgep
Version: 0.0.2
Summary: Geom. extras (geom-extras) for geom-sandbox template [Python].
Project-URL: Homepage, https://github.com/lvjhn/demo-package-python
Project-URL: Bug Tracker, https://github.com/lvjhn/demo-package-python/~/issues
Author-email: "LJ. S.A." <lvjhn.mx@gmail.com>
License: Copyright 2022 LJ S.A.
License-File: LICENSE
Classifier: License :: OSI Approved :: MIT License
Classifier: Operating System :: OS Independent
Classifier: Programming Language :: Python :: 3
Requires-Python: >=3.7
Requires-Dist: beautifulsoup4==4.10.0
Requires-Dist: bleach==6.0.0
Requires-Dist: build==0.10.0
Requires-Dist: catfish==4.16.3
Requires-Dist: certifi==2023.7.22
Requires-Dist: cffi==1.15.1
Requires-Dist: chardet==4.0.0
Requires-Dist: charset-normalizer==3.2.0
Requires-Dist: commonmark==0.9.1
Requires-Dist: cryptography==41.0.3
Requires-Dist: cupshelpers==1.0
Requires-Dist: dbus-python==1.2.18
Requires-Dist: distro==1.7.0
Requires-Dist: docutils==0.20.1
Requires-Dist: faker==13.15.0
Requires-Dist: html5lib==1.1
Requires-Dist: idna==3.4
Requires-Dist: importlib-metadata==6.8.0
Requires-Dist: iniconfig==2.0.0
Requires-Dist: jaraco-classes==3.3.0
Requires-Dist: jeepney==0.8.0
Requires-Dist: keyring==24.2.0
Requires-Dist: lightdm-gtk-greeter-settings==1.2.2
Requires-Dist: lxml==4.8.0
Requires-Dist: mako==1.1.3
Requires-Dist: markdown-it-py==3.0.0
Requires-Dist: markupsafe==2.0.1
Requires-Dist: mdurl==0.1.2
Requires-Dist: menulibre==2.2.2
Requires-Dist: more-itertools==10.0.0
Requires-Dist: mugshot==0.4.3
Requires-Dist: netifaces==0.11.0
Requires-Dist: numpy==1.21.5
Requires-Dist: olefile==0.46
Requires-Dist: onboard==1.4.1
Requires-Dist: packaging==23.1
Requires-Dist: pep517==0.12.0
Requires-Dist: pexpect==4.8.0
Requires-Dist: pillow==9.0.1
Requires-Dist: pkginfo==1.9.6
Requires-Dist: pluggy==1.2.0
Requires-Dist: ply==3.11
Requires-Dist: psutil==5.9.0
Requires-Dist: ptyprocess==0.7.0
Requires-Dist: pycairo==1.20.1
Requires-Dist: pycparser==2.21
Requires-Dist: pycups==2.0.1
Requires-Dist: pygments==2.15.1
Requires-Dist: pygobject==3.42.1
Requires-Dist: pyparsing==3.0.9
Requires-Dist: pyproject-hooks==1.0.0
Requires-Dist: pytest==7.4.0
Requires-Dist: python-apt==2.4.0+ubuntu1
Requires-Dist: python-dateutil==2.8.2
Requires-Dist: pyyaml==5.4.1
Requires-Dist: readme-renderer==40.0
Requires-Dist: reportlab==3.6.8
Requires-Dist: requests-toolbelt==1.0.0
Requires-Dist: requests==2.31.0
Requires-Dist: rfc3986==2.0.0
Requires-Dist: rich==13.5.2
Requires-Dist: scour==0.38.2
Requires-Dist: secretstorage==3.3.3
Requires-Dist: sgt-launcher==0.2.7
Requires-Dist: six==1.16.0
Requires-Dist: soupsieve==2.3.1
Requires-Dist: toml==0.10.2
Requires-Dist: tomli==2.0.1
Requires-Dist: twine==4.0.2
Requires-Dist: ubuntu-advantage-tools==8001
Requires-Dist: ufw==0.36.1
Requires-Dist: urllib3==2.0.4
Requires-Dist: webencodings==0.5.1
Requires-Dist: xcffib==0.11.1
Requires-Dist: zipp==3.16.2
